{
  "resourceType": "ConceptMap",
  "id": "R5-EvidenceReport-R4B-EvidenceReport",
  "extension": [
    {
      "url": "http://hl7.org/fhir/StructureDefinition/package-source",
      "extension": [
        {
          "url": "packageId",
          "valueString": "hl7.fhir.uv.xver.r5-r4b"
        },
        {
          "url": "version",
          "valueString": "0.0.1"
        }
      ]
    }
  ],
  "url": "http://hl7.org/fhir/uv/xver/R5-R4B/ConceptMap/R5-EvidenceReport-R4B-EvidenceReport",
  "name": "R5-EvidenceReport-R4B-EvidenceReport",
  "title": "Concept map to convert a FHIR R5 EvidenceReport into FHIR R4B",
  "sourceScopeCanonical": "http://hl7.org/fhir/StructureDefinition/EvidenceReport|5.0.0",
  "targetScopeCanonical": "http://hl7.org/fhir/StructureDefinition/EvidenceReport|4.3.0",
  "group": [
    {
      "source": "http://hl7.org/fhir/StructureDefinition/EvidenceReport",
      "target": "http://hl7.org/fhir/StructureDefinition/EvidenceReport",
      "element": [
        {
          "code": "EvidenceReport.relatesTo.target",
          "target": [
            {
              "code": "EvidenceReport.relatesTo.target[x]",
              "relationship": "equivalent"
            }
          ]
        },
        {
          "code": "EvidenceReport.relatesTo.target.url",
          "target": [
            {
              "code": "EvidenceReport.relatesTo.target[x].url",
              "relationship": "equivalent"
            }
          ]
        },
        {
          "code": "EvidenceReport.relatesTo.target.identifier",
          "target": [
            {
              "code": "EvidenceReport.relatesTo.target[x].identifier",
              "relationship": "equivalent"
            }
          ]
        },
        {
          "code": "EvidenceReport.relatesTo.target.display",
          "target": [
            {
              "code": "EvidenceReport.relatesTo.target[x].display",
              "relationship": "equivalent"
            }
          ]
        },
        {
          "code": "EvidenceReport.relatesTo.target.resource",
          "target": [
            {
              "code": "EvidenceReport.relatesTo.target[x].resource",
              "relationship": "equivalent"
            }
          ]
        }
      ]
    },
    {
      "source": "http://hl7.org/fhir/StructureDefinition/EvidenceReport",
      "target": "http://hl7.org/fhir/StructureDefinition/EvidenceReport",
      "element": [
        {
          "code": "EvidenceReport",
          "display": "A EvidenceReport",
          "target": [
            {
              "code": "EvidenceReport",
              "display": "A EvidenceReport",
              "relationship": "equivalent",
              "comment": "R5 \u0060EvidenceReport\u0060 maps as Equivalent to R4B \u0060EvidenceReport\u0060"
            }
          ]
        },
        {
          "code": "EvidenceReport.author",
          "display": "Who authored the content",
          "target": [
            {
              "code": "EvidenceReport.author",
              "display": "Who authored the content",
              "relationship": "related-to",
              "comment": "R5 \u0060EvidenceReport.author\u0060 maps as Equivalent to R4B \u0060EvidenceReport.author\u0060"
            }
          ]
        },
        {
          "code": "EvidenceReport.citeAs[x]",
          "display": "Citation for this report",
          "target": [
            {
              "code": "EvidenceReport.citeAs[x]",
              "display": "Citation for this report",
              "relationship": "related-to",
              "comment": "R5 \u0060EvidenceReport.citeAs[x]\u0060 maps as Equivalent to R4B \u0060EvidenceReport.citeAs[x]\u0060"
            }
          ]
        },
        {
          "code": "EvidenceReport.contact",
          "display": "Contact details for the publisher",
          "target": [
            {
              "code": "EvidenceReport.contact",
              "display": "Contact details for the publisher",
              "relationship": "related-to",
              "comment": "R5 \u0060EvidenceReport.contact\u0060 maps as Equivalent to R4B \u0060EvidenceReport.contact\u0060"
            }
          ]
        },
        {
          "code": "EvidenceReport.contained",
          "display": "Contained, inline Resources",
          "target": [
            {
              "code": "EvidenceReport.contained",
              "display": "Contained, inline Resources",
              "relationship": "related-to",
              "comment": "R5 \u0060EvidenceReport.contained\u0060 maps as Equivalent to R4B \u0060EvidenceReport.contained\u0060"
            }
          ]
        },
        {
          "code": "EvidenceReport.editor",
          "display": "Who edited the content",
          "target": [
            {
              "code": "EvidenceReport.editor",
              "display": "Who edited the content",
              "relationship": "related-to",
              "comment": "R5 \u0060EvidenceReport.editor\u0060 maps as Equivalent to R4B \u0060EvidenceReport.editor\u0060"
            }
          ]
        },
        {
          "code": "EvidenceReport.endorser",
          "display": "Who endorsed the content",
          "target": [
            {
              "code": "EvidenceReport.endorser",
              "display": "Who endorsed the content",
              "relationship": "related-to",
              "comment": "R5 \u0060EvidenceReport.endorser\u0060 maps as Equivalent to R4B \u0060EvidenceReport.endorser\u0060"
            }
          ]
        },
        {
          "code": "EvidenceReport.extension",
          "display": "Additional content defined by implementations",
          "target": [
            {
              "code": "EvidenceReport.extension",
              "display": "Additional content defined by implementations",
              "relationship": "related-to",
              "comment": "R5 \u0060EvidenceReport.extension\u0060 maps as SourceIsBroaderThanTarget to R4B \u0060EvidenceReport.extension\u0060 - extension has change due to type change: R5 \u0060extension\u0060 \u0060Extension\u0060 maps as SourceIsBroaderThanTarget for R4B \u0060extension\u0060"
            }
          ]
        },
        {
          "code": "EvidenceReport.id",
          "display": "Logical id of this artifact",
          "target": [
            {
              "code": "EvidenceReport.id",
              "display": "Logical id of this artifact",
              "relationship": "equivalent",
              "comment": "R5 \u0060EvidenceReport.id\u0060 maps as Equivalent to R4B \u0060EvidenceReport.id\u0060"
            }
          ]
        },
        {
          "code": "EvidenceReport.identifier",
          "display": "Unique identifier for the evidence report",
          "target": [
            {
              "code": "EvidenceReport.identifier",
              "display": "Unique identifier for the evidence report",
              "relationship": "related-to",
              "comment": "R5 \u0060EvidenceReport.identifier\u0060 maps as Equivalent to R4B \u0060EvidenceReport.identifier\u0060"
            }
          ]
        },
        {
          "code": "EvidenceReport.implicitRules",
          "display": "A set of rules under which this content was created",
          "target": [
            {
              "code": "EvidenceReport.implicitRules",
              "display": "A set of rules under which this content was created",
              "relationship": "equivalent",
              "comment": "R5 \u0060EvidenceReport.implicitRules\u0060 maps as Equivalent to R4B \u0060EvidenceReport.implicitRules\u0060"
            }
          ]
        },
        {
          "code": "EvidenceReport.language",
          "display": "Language of the resource content",
          "target": [
            {
              "code": "EvidenceReport.language",
              "display": "Language of the resource content",
              "relationship": "related-to",
              "comment": "R5 \u0060EvidenceReport.language\u0060 maps as RelatedTo to R4B \u0060EvidenceReport.language\u0060 - language changed the binding strength from Required to Preferred"
            }
          ]
        },
        {
          "code": "EvidenceReport.meta",
          "display": "Metadata about the resource",
          "target": [
            {
              "code": "EvidenceReport.meta",
              "display": "Metadata about the resource",
              "relationship": "equivalent",
              "comment": "R5 \u0060EvidenceReport.meta\u0060 maps as Equivalent to R4B \u0060EvidenceReport.meta\u0060"
            }
          ]
        },
        {
          "code": "EvidenceReport.modifierExtension",
          "display": "Extensions that cannot be ignored",
          "target": [
            {
              "code": "EvidenceReport.modifierExtension",
              "display": "Extensions that cannot be ignored",
              "relationship": "related-to",
              "comment": "R5 \u0060EvidenceReport.modifierExtension\u0060 maps as SourceIsBroaderThanTarget to R4B \u0060EvidenceReport.modifierExtension\u0060 - modifierExtension has change due to type change: R5 \u0060modifierExtension\u0060 \u0060Extension\u0060 maps as SourceIsBroaderThanTarget for R4B \u0060modifierExtension\u0060"
            }
          ]
        },
        {
          "code": "EvidenceReport.note",
          "display": "Used for footnotes and annotations",
          "target": [
            {
              "code": "EvidenceReport.note",
              "display": "Used for footnotes and annotations",
              "relationship": "related-to",
              "comment": "R5 \u0060EvidenceReport.note\u0060 maps as SourceIsBroaderThanTarget to R4B \u0060EvidenceReport.note\u0060 - note has change due to type change: R5 \u0060note\u0060 \u0060Annotation\u0060 maps as SourceIsBroaderThanTarget for R4B \u0060note\u0060"
            }
          ]
        },
        {
          "code": "EvidenceReport.publisher",
          "display": "Name of the publisher/steward (organization or individual)",
          "target": [
            {
              "code": "EvidenceReport.publisher",
              "display": "Name of the publisher (organization or individual)",
              "relationship": "related-to",
              "comment": "R5 \u0060EvidenceReport.publisher\u0060 maps as Equivalent to R4B \u0060EvidenceReport.publisher\u0060"
            }
          ]
        },
        {
          "code": "EvidenceReport.relatedArtifact",
          "display": "Link, description or reference to artifact associated with the report",
          "target": [
            {
              "code": "EvidenceReport.relatedArtifact",
              "display": "Link, description or reference to artifact associated with the report",
              "relationship": "related-to",
              "comment": "R5 \u0060EvidenceReport.relatedArtifact\u0060 maps as Equivalent to R4B \u0060EvidenceReport.relatedArtifact\u0060"
            }
          ]
        },
        {
          "code": "EvidenceReport.relatedIdentifier",
          "display": "Identifiers for articles that may relate to more than one evidence report",
          "target": [
            {
              "code": "EvidenceReport.relatedIdentifier",
              "display": "Identifiers for articles that may relate to more than one evidence report",
              "relationship": "related-to",
              "comment": "R5 \u0060EvidenceReport.relatedIdentifier\u0060 maps as Equivalent to R4B \u0060EvidenceReport.relatedIdentifier\u0060"
            }
          ]
        },
        {
          "code": "EvidenceReport.relatesTo",
          "display": "Relationships to other compositions/documents",
          "target": [
            {
              "code": "EvidenceReport.relatesTo",
              "display": "Relationships to other compositions/documents",
              "relationship": "related-to",
              "comment": "R5 \u0060EvidenceReport.relatesTo\u0060 maps as Equivalent to R4B \u0060EvidenceReport.relatesTo\u0060"
            }
          ]
        },
        {
          "code": "EvidenceReport.relatesTo.code",
          "display": "replaces | amends | appends | transforms | replacedWith | amendedWith | appendedWith | transformedWith",
          "target": [
            {
              "code": "EvidenceReport.relatesTo.code",
              "display": "replaces | amends | appends | transforms | replacedWith | amendedWith | appendedWith | transformedWith",
              "relationship": "related-to",
              "comment": "R5 \u0060EvidenceReport.relatesTo.code\u0060 maps as Equivalent to R4B \u0060EvidenceReport.relatesTo.code\u0060 - code has compatible required binding for code type: http://hl7.org/fhir/ValueSet/report-relation-type|5.0.0 and http://hl7.org/fhir/ValueSet/report-relation-type|4.3.0 (Equivalent)"
            }
          ]
        },
        {
          "code": "EvidenceReport.relatesTo.extension",
          "display": "Additional content defined by implementations",
          "target": [
            {
              "code": "EvidenceReport.relatesTo.extension",
              "display": "Additional content defined by implementations",
              "relationship": "related-to",
              "comment": "R5 \u0060EvidenceReport.relatesTo.extension\u0060 maps as SourceIsBroaderThanTarget to R4B \u0060EvidenceReport.relatesTo.extension\u0060 - extension has change due to type change: R5 \u0060extension\u0060 \u0060Extension\u0060 maps as SourceIsBroaderThanTarget for R4B \u0060extension\u0060"
            }
          ]
        },
        {
          "code": "EvidenceReport.relatesTo.id",
          "display": "Unique id for inter-element referencing",
          "target": [
            {
              "code": "EvidenceReport.relatesTo.id",
              "display": "Unique id for inter-element referencing",
              "relationship": "related-to",
              "comment": "R5 \u0060EvidenceReport.relatesTo.id\u0060 maps as Equivalent to R4B \u0060EvidenceReport.relatesTo.id\u0060"
            }
          ]
        },
        {
          "code": "EvidenceReport.relatesTo.modifierExtension",
          "display": "Extensions that cannot be ignored even if unrecognized",
          "target": [
            {
              "code": "EvidenceReport.relatesTo.modifierExtension",
              "display": "Extensions that cannot be ignored even if unrecognized",
              "relationship": "related-to",
              "comment": "R5 \u0060EvidenceReport.relatesTo.modifierExtension\u0060 maps as SourceIsBroaderThanTarget to R4B \u0060EvidenceReport.relatesTo.modifierExtension\u0060 - modifierExtension has change due to type change: R5 \u0060modifierExtension\u0060 \u0060Extension\u0060 maps as SourceIsBroaderThanTarget for R4B \u0060modifierExtension\u0060"
            }
          ]
        },
        {
          "code": "EvidenceReport.relatesTo.target",
          "display": "Target of the relationship",
          "noMap": true
        },
        {
          "code": "EvidenceReport.relatesTo.target.display",
          "display": "Target of the relationship Display",
          "noMap": true
        },
        {
          "code": "EvidenceReport.relatesTo.target.extension",
          "display": "Additional content defined by implementations",
          "noMap": true
        },
        {
          "code": "EvidenceReport.relatesTo.target.id",
          "display": "Unique id for inter-element referencing",
          "noMap": true
        },
        {
          "code": "EvidenceReport.relatesTo.target.identifier",
          "display": "Target of the relationship Identifier",
          "noMap": true
        },
        {
          "code": "EvidenceReport.relatesTo.target.modifierExtension",
          "display": "Extensions that cannot be ignored even if unrecognized",
          "noMap": true
        },
        {
          "code": "EvidenceReport.relatesTo.target.resource",
          "display": "Target of the relationship Resource reference",
          "noMap": true
        },
        {
          "code": "EvidenceReport.relatesTo.target.url",
          "display": "Target of the relationship URL",
          "noMap": true
        },
        {
          "code": "EvidenceReport.reviewer",
          "display": "Who reviewed the content",
          "target": [
            {
              "code": "EvidenceReport.reviewer",
              "display": "Who reviewed the content",
              "relationship": "related-to",
              "comment": "R5 \u0060EvidenceReport.reviewer\u0060 maps as Equivalent to R4B \u0060EvidenceReport.reviewer\u0060"
            }
          ]
        },
        {
          "code": "EvidenceReport.section",
          "display": "Composition is broken into sections",
          "target": [
            {
              "code": "EvidenceReport.section",
              "display": "Composition is broken into sections",
              "relationship": "related-to",
              "comment": "R5 \u0060EvidenceReport.section\u0060 maps as Equivalent to R4B \u0060EvidenceReport.section\u0060"
            }
          ]
        },
        {
          "code": "EvidenceReport.section.author",
          "display": "Who and/or what authored the section",
          "target": [
            {
              "code": "EvidenceReport.section.author",
              "display": "Who and/or what authored the section",
              "relationship": "related-to",
              "comment": "R5 \u0060EvidenceReport.section.author\u0060 maps as RelatedTo to R4B \u0060EvidenceReport.section.author\u0060 - author has change due to type change: R5 \u0060author\u0060 \u0060Reference\u0060 maps as RelatedTo for R4B \u0060author\u0060"
            }
          ]
        },
        {
          "code": "EvidenceReport.section.emptyReason",
          "display": "Why the section is empty",
          "target": [
            {
              "code": "EvidenceReport.section.emptyReason",
              "display": "Why the section is empty",
              "relationship": "related-to",
              "comment": "R5 \u0060EvidenceReport.section.emptyReason\u0060 maps as Equivalent to R4B \u0060EvidenceReport.section.emptyReason\u0060"
            }
          ]
        },
        {
          "code": "EvidenceReport.section.entryClassifier",
          "display": "Extensible classifiers as content",
          "target": [
            {
              "code": "EvidenceReport.section.entryClassifier",
              "display": "Extensible classifiers as content",
              "relationship": "related-to",
              "comment": "R5 \u0060EvidenceReport.section.entryClassifier\u0060 maps as Equivalent to R4B \u0060EvidenceReport.section.entryClassifier\u0060"
            }
          ]
        },
        {
          "code": "EvidenceReport.section.entryQuantity",
          "display": "Quantity as content",
          "target": [
            {
              "code": "EvidenceReport.section.entryQuantity",
              "display": "Quantity as content",
              "relationship": "related-to",
              "comment": "R5 \u0060EvidenceReport.section.entryQuantity\u0060 maps as Equivalent to R4B \u0060EvidenceReport.section.entryQuantity\u0060"
            }
          ]
        },
        {
          "code": "EvidenceReport.section.entryReference",
          "display": "Reference to resources as content",
          "target": [
            {
              "code": "EvidenceReport.section.entryReference",
              "display": "Reference to resources as content",
              "relationship": "related-to",
              "comment": "R5 \u0060EvidenceReport.section.entryReference\u0060 maps as Equivalent to R4B \u0060EvidenceReport.section.entryReference\u0060"
            }
          ]
        },
        {
          "code": "EvidenceReport.section.extension",
          "display": "Additional content defined by implementations",
          "target": [
            {
              "code": "EvidenceReport.section.extension",
              "display": "Additional content defined by implementations",
              "relationship": "related-to",
              "comment": "R5 \u0060EvidenceReport.section.extension\u0060 maps as SourceIsBroaderThanTarget to R4B \u0060EvidenceReport.section.extension\u0060 - extension has change due to type change: R5 \u0060extension\u0060 \u0060Extension\u0060 maps as SourceIsBroaderThanTarget for R4B \u0060extension\u0060"
            }
          ]
        },
        {
          "code": "EvidenceReport.section.focus",
          "display": "Classification of section (recommended)",
          "target": [
            {
              "code": "EvidenceReport.section.focus",
              "display": "Classification of section (recommended)",
              "relationship": "related-to",
              "comment": "R5 \u0060EvidenceReport.section.focus\u0060 maps as Equivalent to R4B \u0060EvidenceReport.section.focus\u0060"
            }
          ]
        },
        {
          "code": "EvidenceReport.section.focusReference",
          "display": "Classification of section by Resource",
          "target": [
            {
              "code": "EvidenceReport.section.focusReference",
              "display": "Classification of section by Resource",
              "relationship": "related-to",
              "comment": "R5 \u0060EvidenceReport.section.focusReference\u0060 maps as Equivalent to R4B \u0060EvidenceReport.section.focusReference\u0060"
            }
          ]
        },
        {
          "code": "EvidenceReport.section.id",
          "display": "Unique id for inter-element referencing",
          "target": [
            {
              "code": "EvidenceReport.section.id",
              "display": "Unique id for inter-element referencing",
              "relationship": "related-to",
              "comment": "R5 \u0060EvidenceReport.section.id\u0060 maps as Equivalent to R4B \u0060EvidenceReport.section.id\u0060"
            }
          ]
        },
        {
          "code": "EvidenceReport.section.mode",
          "display": "working | snapshot | changes",
          "target": [
            {
              "code": "EvidenceReport.section.mode",
              "display": "working | snapshot | changes",
              "relationship": "related-to",
              "comment": "R5 \u0060EvidenceReport.section.mode\u0060 maps as Equivalent to R4B \u0060EvidenceReport.section.mode\u0060 - mode has compatible required binding for code type: http://hl7.org/fhir/ValueSet/list-mode|5.0.0 and http://hl7.org/fhir/ValueSet/list-mode|4.3.0 (Equivalent)"
            }
          ]
        },
        {
          "code": "EvidenceReport.section.modifierExtension",
          "display": "Extensions that cannot be ignored even if unrecognized",
          "target": [
            {
              "code": "EvidenceReport.section.modifierExtension",
              "display": "Extensions that cannot be ignored even if unrecognized",
              "relationship": "related-to",
              "comment": "R5 \u0060EvidenceReport.section.modifierExtension\u0060 maps as SourceIsBroaderThanTarget to R4B \u0060EvidenceReport.section.modifierExtension\u0060 - modifierExtension has change due to type change: R5 \u0060modifierExtension\u0060 \u0060Extension\u0060 maps as SourceIsBroaderThanTarget for R4B \u0060modifierExtension\u0060"
            }
          ]
        },
        {
          "code": "EvidenceReport.section.orderedBy",
          "display": "Order of section entries",
          "target": [
            {
              "code": "EvidenceReport.section.orderedBy",
              "display": "Order of section entries",
              "relationship": "related-to",
              "comment": "R5 \u0060EvidenceReport.section.orderedBy\u0060 maps as Equivalent to R4B \u0060EvidenceReport.section.orderedBy\u0060"
            }
          ]
        },
        {
          "code": "EvidenceReport.section.section",
          "display": "Nested Section",
          "target": [
            {
              "code": "EvidenceReport.section.section",
              "display": "Nested Section",
              "relationship": "related-to",
              "comment": "R5 \u0060EvidenceReport.section.section\u0060 maps as Equivalent to R4B \u0060EvidenceReport.section.section\u0060"
            }
          ]
        },
        {
          "code": "EvidenceReport.section.text",
          "display": "Text summary of the section, for human interpretation",
          "target": [
            {
              "code": "EvidenceReport.section.text",
              "display": "Text summary of the section, for human interpretation",
              "relationship": "related-to",
              "comment": "R5 \u0060EvidenceReport.section.text\u0060 maps as Equivalent to R4B \u0060EvidenceReport.section.text\u0060"
            }
          ]
        },
        {
          "code": "EvidenceReport.section.title",
          "display": "Label for section (e.g. for ToC)",
          "target": [
            {
              "code": "EvidenceReport.section.title",
              "display": "Label for section (e.g. for ToC)",
              "relationship": "related-to",
              "comment": "R5 \u0060EvidenceReport.section.title\u0060 maps as Equivalent to R4B \u0060EvidenceReport.section.title\u0060"
            }
          ]
        },
        {
          "code": "EvidenceReport.status",
          "display": "draft | active | retired | unknown",
          "target": [
            {
              "code": "EvidenceReport.status",
              "display": "draft | active | retired | unknown",
              "relationship": "related-to",
              "comment": "R5 \u0060EvidenceReport.status\u0060 maps as Equivalent to R4B \u0060EvidenceReport.status\u0060 - status has compatible required binding for code type: http://hl7.org/fhir/ValueSet/publication-status|5.0.0 and http://hl7.org/fhir/ValueSet/publication-status|4.3.0 (Equivalent)"
            }
          ]
        },
        {
          "code": "EvidenceReport.subject",
          "display": "Focus of the report",
          "target": [
            {
              "code": "EvidenceReport.subject",
              "display": "Focus of the report",
              "relationship": "related-to",
              "comment": "R5 \u0060EvidenceReport.subject\u0060 maps as Equivalent to R4B \u0060EvidenceReport.subject\u0060"
            }
          ]
        },
        {
          "code": "EvidenceReport.subject.characteristic",
          "display": "Characteristic",
          "target": [
            {
              "code": "EvidenceReport.subject.characteristic",
              "display": "Characteristic",
              "relationship": "related-to",
              "comment": "R5 \u0060EvidenceReport.subject.characteristic\u0060 maps as Equivalent to R4B \u0060EvidenceReport.subject.characteristic\u0060"
            }
          ]
        },
        {
          "code": "EvidenceReport.subject.characteristic.code",
          "display": "Characteristic code",
          "target": [
            {
              "code": "EvidenceReport.subject.characteristic.code",
              "display": "Characteristic code",
              "relationship": "related-to",
              "comment": "R5 \u0060EvidenceReport.subject.characteristic.code\u0060 maps as Equivalent to R4B \u0060EvidenceReport.subject.characteristic.code\u0060"
            }
          ]
        },
        {
          "code": "EvidenceReport.subject.characteristic.exclude",
          "display": "Is used to express not the characteristic",
          "target": [
            {
              "code": "EvidenceReport.subject.characteristic.exclude",
              "display": "Is used to express not the characteristic",
              "relationship": "related-to",
              "comment": "R5 \u0060EvidenceReport.subject.characteristic.exclude\u0060 maps as Equivalent to R4B \u0060EvidenceReport.subject.characteristic.exclude\u0060"
            }
          ]
        },
        {
          "code": "EvidenceReport.subject.characteristic.extension",
          "display": "Additional content defined by implementations",
          "target": [
            {
              "code": "EvidenceReport.subject.characteristic.extension",
              "display": "Additional content defined by implementations",
              "relationship": "related-to",
              "comment": "R5 \u0060EvidenceReport.subject.characteristic.extension\u0060 maps as SourceIsBroaderThanTarget to R4B \u0060EvidenceReport.subject.characteristic.extension\u0060 - extension has change due to type change: R5 \u0060extension\u0060 \u0060Extension\u0060 maps as SourceIsBroaderThanTarget for R4B \u0060extension\u0060"
            }
          ]
        },
        {
          "code": "EvidenceReport.subject.characteristic.id",
          "display": "Unique id for inter-element referencing",
          "target": [
            {
              "code": "EvidenceReport.subject.characteristic.id",
              "display": "Unique id for inter-element referencing",
              "relationship": "related-to",
              "comment": "R5 \u0060EvidenceReport.subject.characteristic.id\u0060 maps as Equivalent to R4B \u0060EvidenceReport.subject.characteristic.id\u0060"
            }
          ]
        },
        {
          "code": "EvidenceReport.subject.characteristic.modifierExtension",
          "display": "Extensions that cannot be ignored even if unrecognized",
          "target": [
            {
              "code": "EvidenceReport.subject.characteristic.modifierExtension",
              "display": "Extensions that cannot be ignored even if unrecognized",
              "relationship": "related-to",
              "comment": "R5 \u0060EvidenceReport.subject.characteristic.modifierExtension\u0060 maps as SourceIsBroaderThanTarget to R4B \u0060EvidenceReport.subject.characteristic.modifierExtension\u0060 - modifierExtension has change due to type change: R5 \u0060modifierExtension\u0060 \u0060Extension\u0060 maps as SourceIsBroaderThanTarget for R4B \u0060modifierExtension\u0060"
            }
          ]
        },
        {
          "code": "EvidenceReport.subject.characteristic.period",
          "display": "Timeframe for the characteristic",
          "target": [
            {
              "code": "EvidenceReport.subject.characteristic.period",
              "display": "Timeframe for the characteristic",
              "relationship": "related-to",
              "comment": "R5 \u0060EvidenceReport.subject.characteristic.period\u0060 maps as Equivalent to R4B \u0060EvidenceReport.subject.characteristic.period\u0060"
            }
          ]
        },
        {
          "code": "EvidenceReport.subject.characteristic.value[x]",
          "display": "Characteristic value",
          "target": [
            {
              "code": "EvidenceReport.subject.characteristic.value[x]",
              "display": "Characteristic value",
              "relationship": "related-to",
              "comment": "R5 \u0060EvidenceReport.subject.characteristic.value[x]\u0060 maps as Equivalent to R4B \u0060EvidenceReport.subject.characteristic.value[x]\u0060"
            }
          ]
        },
        {
          "code": "EvidenceReport.subject.extension",
          "display": "Additional content defined by implementations",
          "target": [
            {
              "code": "EvidenceReport.subject.extension",
              "display": "Additional content defined by implementations",
              "relationship": "related-to",
              "comment": "R5 \u0060EvidenceReport.subject.extension\u0060 maps as SourceIsBroaderThanTarget to R4B \u0060EvidenceReport.subject.extension\u0060 - extension has change due to type change: R5 \u0060extension\u0060 \u0060Extension\u0060 maps as SourceIsBroaderThanTarget for R4B \u0060extension\u0060"
            }
          ]
        },
        {
          "code": "EvidenceReport.subject.id",
          "display": "Unique id for inter-element referencing",
          "target": [
            {
              "code": "EvidenceReport.subject.id",
              "display": "Unique id for inter-element referencing",
              "relationship": "related-to",
              "comment": "R5 \u0060EvidenceReport.subject.id\u0060 maps as Equivalent to R4B \u0060EvidenceReport.subject.id\u0060"
            }
          ]
        },
        {
          "code": "EvidenceReport.subject.modifierExtension",
          "display": "Extensions that cannot be ignored even if unrecognized",
          "target": [
            {
              "code": "EvidenceReport.subject.modifierExtension",
              "display": "Extensions that cannot be ignored even if unrecognized",
              "relationship": "related-to",
              "comment": "R5 \u0060EvidenceReport.subject.modifierExtension\u0060 maps as SourceIsBroaderThanTarget to R4B \u0060EvidenceReport.subject.modifierExtension\u0060 - modifierExtension has change due to type change: R5 \u0060modifierExtension\u0060 \u0060Extension\u0060 maps as SourceIsBroaderThanTarget for R4B \u0060modifierExtension\u0060"
            }
          ]
        },
        {
          "code": "EvidenceReport.subject.note",
          "display": "Footnotes and/or explanatory notes",
          "target": [
            {
              "code": "EvidenceReport.subject.note",
              "display": "Footnotes and/or explanatory notes",
              "relationship": "related-to",
              "comment": "R5 \u0060EvidenceReport.subject.note\u0060 maps as SourceIsBroaderThanTarget to R4B \u0060EvidenceReport.subject.note\u0060 - note has change due to type change: R5 \u0060note\u0060 \u0060Annotation\u0060 maps as SourceIsBroaderThanTarget for R4B \u0060note\u0060"
            }
          ]
        },
        {
          "code": "EvidenceReport.text",
          "display": "Text summary of the resource, for human interpretation",
          "target": [
            {
              "code": "EvidenceReport.text",
              "display": "Text summary of the resource, for human interpretation",
              "relationship": "related-to",
              "comment": "R5 \u0060EvidenceReport.text\u0060 maps as Equivalent to R4B \u0060EvidenceReport.text\u0060"
            }
          ]
        },
        {
          "code": "EvidenceReport.type",
          "display": "Kind of report",
          "target": [
            {
              "code": "EvidenceReport.type",
              "display": "Kind of report",
              "relationship": "related-to",
              "comment": "R5 \u0060EvidenceReport.type\u0060 maps as Equivalent to R4B \u0060EvidenceReport.type\u0060"
            }
          ]
        },
        {
          "code": "EvidenceReport.url",
          "display": "Canonical identifier for this EvidenceReport, represented as a globally unique URI",
          "target": [
            {
              "code": "EvidenceReport.url",
              "display": "Canonical identifier for this EvidenceReport, represented as a globally unique URI",
              "relationship": "related-to",
              "comment": "R5 \u0060EvidenceReport.url\u0060 maps as Equivalent to R4B \u0060EvidenceReport.url\u0060"
            }
          ]
        },
        {
          "code": "EvidenceReport.useContext",
          "display": "The context that the content is intended to support",
          "target": [
            {
              "code": "EvidenceReport.useContext",
              "display": "The context that the content is intended to support",
              "relationship": "related-to",
              "comment": "R5 \u0060EvidenceReport.useContext\u0060 maps as Equivalent to R4B \u0060EvidenceReport.useContext\u0060"
            }
          ]
        }
      ]
    }
  ]
}