{
  "resourceType": "ValueSet",
  "id": "R2-v3-SpecimenType-for-R5",
  "extension": [
    {
      "url": "http://hl7.org/fhir/StructureDefinition/structuredefinition-wg",
      "valueCode": "fhir"
    },
    {
      "extension": [
        {
          "url": "packageId",
          "valueId": "hl7.fhir.uv.xver-r2.r5"
        },
        {
          "url": "version",
          "valueString": "0.0.1-snapshot-2"
        }
      ],
      "url": "http://hl7.org/fhir/StructureDefinition/package-source"
    }
  ],
  "url": "http://hl7.org/fhir/1.0/ValueSet/R2-v3-SpecimenType-for-R5",
  "version": "0.0.1-snapshot-2",
  "name": "R2_v3_SpecimenType_for_R5",
  "title": "Cross-version VS for R2.v3 Code System SpecimenType for use in FHIR R5",
  "status": "active",
  "experimental": false,
  "date": "2025-08-27T10:01:44.0346096-05:00",
  "publisher": "FHIR Infrastructure",
  "contact": [
    {
      "name": "FHIR Infrastructure",
      "telecom": [
        {
          "system": "url",
          "value": "http://www.hl7.org/Special/committees/fiwg"
        }
      ]
    }
  ],
  "description": "This cross-version ValueSet represents concepts from http://hl7.org/fhir/ValueSet/v3-SpecimenType|2015-07-31 for use in FHIR R5. Concepts not present here have direct `equivalent` mappings crossing all versions from R2 to R5.",
  "compose": {
    "include": [
      {
        "system": "http://hl7.org/fhir/v3/SpecimenType",
        "version": "1.0.2",
        "concept": [
          {
            "code": "ABS",
            "display": "Abcess"
          },
          {
            "code": "AMN",
            "display": "Amniotic fluid"
          },
          {
            "code": "ASP",
            "display": "Aspirate"
          },
          {
            "code": "BBL",
            "display": "Blood bag"
          },
          {
            "code": "BDY",
            "display": "Whole body"
          },
          {
            "code": "BIFL",
            "display": "Bile fluid"
          },
          {
            "code": "BLD",
            "display": "Whole blood"
          },
          {
            "code": "BLDA",
            "display": "Blood arterial"
          },
          {
            "code": "BLDC",
            "display": "Blood capillary"
          },
          {
            "code": "BLDCO",
            "display": "Blood - cord"
          },
          {
            "code": "BLDV",
            "display": "Blood venous"
          },
          {
            "code": "BON",
            "display": "Bone"
          },
          {
            "code": "BPH",
            "display": "Basophils"
          },
          {
            "code": "BPU",
            "display": "Blood product unit"
          },
          {
            "code": "BRN",
            "display": "Burn"
          },
          {
            "code": "BRO",
            "display": "Bronchial"
          },
          {
            "code": "BRTH",
            "display": "Exhaled gas (=breath)"
          },
          {
            "code": "CALC",
            "display": "Calculus (=Stone)"
          },
          {
            "code": "CDM",
            "display": "Cardiac muscle"
          },
          {
            "code": "CNJT",
            "display": "Conjunctiva"
          },
          {
            "code": "CNL",
            "display": "Cannula"
          },
          {
            "code": "COL",
            "display": "Colostrum"
          },
          {
            "code": "CRN",
            "display": "Cornea"
          },
          {
            "code": "CSF",
            "display": "Cerebral spinal fluid"
          },
          {
            "code": "CTP",
            "display": "Catheter tip"
          },
          {
            "code": "CUR",
            "display": "Curettage"
          },
          {
            "code": "CVM",
            "display": "Cervical mucus"
          },
          {
            "code": "CVX",
            "display": "Cervix"
          },
          {
            "code": "CYST",
            "display": "Cyst"
          },
          {
            "code": "DIAF",
            "display": "Dialysis fluid"
          },
          {
            "code": "DOSE",
            "display": "Dose med or substance"
          },
          {
            "code": "DRN",
            "display": "Drain"
          },
          {
            "code": "DUFL",
            "display": "Duodenal fluid"
          },
          {
            "code": "EAR",
            "display": "Ear"
          },
          {
            "code": "EARW",
            "display": "Ear wax (cerumen)"
          },
          {
            "code": "ELT",
            "display": "Electrode"
          },
          {
            "code": "ENDC",
            "display": "Endocardium"
          },
          {
            "code": "ENDM",
            "display": "Endometrium"
          },
          {
            "code": "EOS",
            "display": "Eosinophils"
          },
          {
            "code": "EYE",
            "display": "Eye"
          },
          {
            "code": "FIB",
            "display": "Fibroblasts"
          },
          {
            "code": "FIST",
            "display": "Fistula"
          },
          {
            "code": "FLT",
            "display": "Filter"
          },
          {
            "code": "FLU",
            "display": "Body fluid, unsp"
          },
          {
            "code": "FOOD",
            "display": "Food sample"
          },
          {
            "code": "GAS",
            "display": "Gas"
          },
          {
            "code": "GAST",
            "display": "Gastric fluid/contents"
          },
          {
            "code": "GEN",
            "display": "Genital"
          },
          {
            "code": "GENC",
            "display": "Genital cervix"
          },
          {
            "code": "GENF",
            "display": "Genital fluid"
          },
          {
            "code": "GENL",
            "display": "Genital lochia"
          },
          {
            "code": "GENV",
            "display": "Genital vaginal"
          },
          {
            "code": "HAR",
            "display": "Hair"
          },
          {
            "code": "IHG",
            "display": "Inhaled Gas"
          },
          {
            "code": "ISLT",
            "display": "Isolate"
          },
          {
            "code": "IT",
            "display": "Intubation tube"
          },
          {
            "code": "LAM",
            "display": "Lamella"
          },
          {
            "code": "LIQ",
            "display": "Liquid NOS"
          },
          {
            "code": "LN",
            "display": "Line"
          },
          {
            "code": "LNA",
            "display": "Line arterial"
          },
          {
            "code": "LNV",
            "display": "Line venous"
          },
          {
            "code": "LYM",
            "display": "Lymphocytes"
          },
          {
            "code": "MAC",
            "display": "Macrophages"
          },
          {
            "code": "MAR",
            "display": "Marrow (bone)"
          },
          {
            "code": "MBLD",
            "display": "Menstrual blood"
          },
          {
            "code": "MEC",
            "display": "Meconium"
          },
          {
            "code": "MILK",
            "display": "Breast milk"
          },
          {
            "code": "MLK",
            "display": "Milk"
          },
          {
            "code": "NAIL",
            "display": "Nail"
          },
          {
            "code": "NOS",
            "display": "Nose (nasal passage)"
          },
          {
            "code": "PAFL",
            "display": "Pancreatic fluid"
          },
          {
            "code": "PAT",
            "display": "Patient"
          },
          {
            "code": "PLAS",
            "display": "Plasma"
          },
          {
            "code": "PLB",
            "display": "Plasma bag"
          },
          {
            "code": "PLC",
            "display": "Placenta"
          },
          {
            "code": "PLR",
            "display": "Pleural fluid (thoracentesis fld)"
          },
          {
            "code": "PMN",
            "display": "Polymorphonuclear neutrophils"
          },
          {
            "code": "PPP",
            "display": "Platelet poor plasma"
          },
          {
            "code": "PRP",
            "display": "Platelet rich plasma"
          },
          {
            "code": "PRT",
            "display": "Peritoneal fluid /ascites"
          },
          {
            "code": "PUS",
            "display": "Pus"
          },
          {
            "code": "RBC",
            "display": "Erythrocytes"
          },
          {
            "code": "SAL",
            "display": "Saliva"
          },
          {
            "code": "SER",
            "display": "Serum"
          },
          {
            "code": "SKM",
            "display": "Skeletal muscle"
          },
          {
            "code": "SKN",
            "display": "Skin"
          },
          {
            "code": "SMN",
            "display": "Seminal fluid"
          },
          {
            "code": "SMPLS",
            "display": "Seminal plasma"
          },
          {
            "code": "SNV",
            "display": "Synovial fluid (Joint fluid)"
          },
          {
            "code": "SPRM",
            "display": "Spermatozoa"
          },
          {
            "code": "SPT",
            "display": "Sputum"
          },
          {
            "code": "SPTC",
            "display": "Sputum - coughed"
          },
          {
            "code": "SPTT",
            "display": "Sputum - tracheal aspirate"
          },
          {
            "code": "STL",
            "display": "Stool = Fecal"
          },
          {
            "code": "SWT",
            "display": "Sweat"
          },
          {
            "code": "TEAR",
            "display": "Tears"
          },
          {
            "code": "THRB",
            "display": "Thrombocyte (platelet)"
          },
          {
            "code": "THRT",
            "display": "Throat"
          },
          {
            "code": "TISG",
            "display": "Tissue gall bladder"
          },
          {
            "code": "TISPL",
            "display": "Tissue placenta"
          },
          {
            "code": "TISS",
            "display": "Tissue, unspecified"
          },
          {
            "code": "TISU",
            "display": "Tissue ulcer"
          },
          {
            "code": "TLGI",
            "display": "Tissue large intestine"
          },
          {
            "code": "TLNG",
            "display": "Tissue lung"
          },
          {
            "code": "TSMI",
            "display": "Tissue small intestine Tissue ulcer"
          },
          {
            "code": "TUB",
            "display": "Tube, unspecified"
          },
          {
            "code": "ULC",
            "display": "Ulcer"
          },
          {
            "code": "UMB",
            "display": "Umbilical blood"
          },
          {
            "code": "UMED",
            "display": "Unknown medicine"
          },
          {
            "code": "UR",
            "display": "Urine"
          },
          {
            "code": "URC",
            "display": "Urine clean catch"
          },
          {
            "code": "URNS",
            "display": "Urine sediment"
          },
          {
            "code": "URT",
            "display": "Urine catheter"
          },
          {
            "code": "URTH",
            "display": "Urethra"
          },
          {
            "code": "USUB",
            "display": "Unknown substance"
          },
          {
            "code": "VOM",
            "display": "Vomitus"
          },
          {
            "code": "WAT",
            "display": "Water"
          },
          {
            "code": "WBC",
            "display": "Leukocytes"
          },
          {
            "code": "WICK",
            "display": "Wick"
          },
          {
            "code": "WND",
            "display": "Wound"
          },
          {
            "code": "WNDA",
            "display": "Wound abscess"
          },
          {
            "code": "WNDD",
            "display": "Wound drainage"
          },
          {
            "code": "WNDE",
            "display": "Wound exudate"
          }
        ]
      }
    ]
  },
  "expansion": {
    "timestamp": "2025-08-27T10:01:44.0345274-05:00",
    "contains": [
      {
        "system": "http://hl7.org/fhir/v3/SpecimenType",
        "version": "1.0.2",
        "code": "ABS",
        "display": "Abcess"
      },
      {
        "system": "http://hl7.org/fhir/v3/SpecimenType",
        "version": "1.0.2",
        "code": "AMN",
        "display": "Amniotic fluid"
      },
      {
        "system": "http://hl7.org/fhir/v3/SpecimenType",
        "version": "1.0.2",
        "code": "ASP",
        "display": "Aspirate"
      },
      {
        "system": "http://hl7.org/fhir/v3/SpecimenType",
        "version": "1.0.2",
        "code": "BBL",
        "display": "Blood bag"
      },
      {
        "system": "http://hl7.org/fhir/v3/SpecimenType",
        "version": "1.0.2",
        "code": "BDY",
        "display": "Whole body"
      },
      {
        "system": "http://hl7.org/fhir/v3/SpecimenType",
        "version": "1.0.2",
        "code": "BIFL",
        "display": "Bile fluid"
      },
      {
        "system": "http://hl7.org/fhir/v3/SpecimenType",
        "version": "1.0.2",
        "code": "BLD",
        "display": "Whole blood"
      },
      {
        "system": "http://hl7.org/fhir/v3/SpecimenType",
        "version": "1.0.2",
        "code": "BLDA",
        "display": "Blood arterial"
      },
      {
        "system": "http://hl7.org/fhir/v3/SpecimenType",
        "version": "1.0.2",
        "code": "BLDC",
        "display": "Blood capillary"
      },
      {
        "system": "http://hl7.org/fhir/v3/SpecimenType",
        "version": "1.0.2",
        "code": "BLDCO",
        "display": "Blood - cord"
      },
      {
        "system": "http://hl7.org/fhir/v3/SpecimenType",
        "version": "1.0.2",
        "code": "BLDV",
        "display": "Blood venous"
      },
      {
        "system": "http://hl7.org/fhir/v3/SpecimenType",
        "version": "1.0.2",
        "code": "BON",
        "display": "Bone"
      },
      {
        "system": "http://hl7.org/fhir/v3/SpecimenType",
        "version": "1.0.2",
        "code": "BPH",
        "display": "Basophils"
      },
      {
        "system": "http://hl7.org/fhir/v3/SpecimenType",
        "version": "1.0.2",
        "code": "BPU",
        "display": "Blood product unit"
      },
      {
        "system": "http://hl7.org/fhir/v3/SpecimenType",
        "version": "1.0.2",
        "code": "BRN",
        "display": "Burn"
      },
      {
        "system": "http://hl7.org/fhir/v3/SpecimenType",
        "version": "1.0.2",
        "code": "BRO",
        "display": "Bronchial"
      },
      {
        "system": "http://hl7.org/fhir/v3/SpecimenType",
        "version": "1.0.2",
        "code": "BRTH",
        "display": "Exhaled gas (=breath)"
      },
      {
        "system": "http://hl7.org/fhir/v3/SpecimenType",
        "version": "1.0.2",
        "code": "CALC",
        "display": "Calculus (=Stone)"
      },
      {
        "system": "http://hl7.org/fhir/v3/SpecimenType",
        "version": "1.0.2",
        "code": "CDM",
        "display": "Cardiac muscle"
      },
      {
        "system": "http://hl7.org/fhir/v3/SpecimenType",
        "version": "1.0.2",
        "code": "CNJT",
        "display": "Conjunctiva"
      },
      {
        "system": "http://hl7.org/fhir/v3/SpecimenType",
        "version": "1.0.2",
        "code": "CNL",
        "display": "Cannula"
      },
      {
        "system": "http://hl7.org/fhir/v3/SpecimenType",
        "version": "1.0.2",
        "code": "COL",
        "display": "Colostrum"
      },
      {
        "system": "http://hl7.org/fhir/v3/SpecimenType",
        "version": "1.0.2",
        "code": "CRN",
        "display": "Cornea"
      },
      {
        "system": "http://hl7.org/fhir/v3/SpecimenType",
        "version": "1.0.2",
        "code": "CSF",
        "display": "Cerebral spinal fluid"
      },
      {
        "system": "http://hl7.org/fhir/v3/SpecimenType",
        "version": "1.0.2",
        "code": "CTP",
        "display": "Catheter tip"
      },
      {
        "system": "http://hl7.org/fhir/v3/SpecimenType",
        "version": "1.0.2",
        "code": "CUR",
        "display": "Curettage"
      },
      {
        "system": "http://hl7.org/fhir/v3/SpecimenType",
        "version": "1.0.2",
        "code": "CVM",
        "display": "Cervical mucus"
      },
      {
        "system": "http://hl7.org/fhir/v3/SpecimenType",
        "version": "1.0.2",
        "code": "CVX",
        "display": "Cervix"
      },
      {
        "system": "http://hl7.org/fhir/v3/SpecimenType",
        "version": "1.0.2",
        "code": "CYST",
        "display": "Cyst"
      },
      {
        "system": "http://hl7.org/fhir/v3/SpecimenType",
        "version": "1.0.2",
        "code": "DIAF",
        "display": "Dialysis fluid"
      },
      {
        "system": "http://hl7.org/fhir/v3/SpecimenType",
        "version": "1.0.2",
        "code": "DOSE",
        "display": "Dose med or substance"
      },
      {
        "system": "http://hl7.org/fhir/v3/SpecimenType",
        "version": "1.0.2",
        "code": "DRN",
        "display": "Drain"
      },
      {
        "system": "http://hl7.org/fhir/v3/SpecimenType",
        "version": "1.0.2",
        "code": "DUFL",
        "display": "Duodenal fluid"
      },
      {
        "system": "http://hl7.org/fhir/v3/SpecimenType",
        "version": "1.0.2",
        "code": "EAR",
        "display": "Ear"
      },
      {
        "system": "http://hl7.org/fhir/v3/SpecimenType",
        "version": "1.0.2",
        "code": "EARW",
        "display": "Ear wax (cerumen)"
      },
      {
        "system": "http://hl7.org/fhir/v3/SpecimenType",
        "version": "1.0.2",
        "code": "ELT",
        "display": "Electrode"
      },
      {
        "system": "http://hl7.org/fhir/v3/SpecimenType",
        "version": "1.0.2",
        "code": "ENDC",
        "display": "Endocardium"
      },
      {
        "system": "http://hl7.org/fhir/v3/SpecimenType",
        "version": "1.0.2",
        "code": "ENDM",
        "display": "Endometrium"
      },
      {
        "system": "http://hl7.org/fhir/v3/SpecimenType",
        "version": "1.0.2",
        "code": "EOS",
        "display": "Eosinophils"
      },
      {
        "system": "http://hl7.org/fhir/v3/SpecimenType",
        "version": "1.0.2",
        "code": "EYE",
        "display": "Eye"
      },
      {
        "system": "http://hl7.org/fhir/v3/SpecimenType",
        "version": "1.0.2",
        "code": "FIB",
        "display": "Fibroblasts"
      },
      {
        "system": "http://hl7.org/fhir/v3/SpecimenType",
        "version": "1.0.2",
        "code": "FIST",
        "display": "Fistula"
      },
      {
        "system": "http://hl7.org/fhir/v3/SpecimenType",
        "version": "1.0.2",
        "code": "FLT",
        "display": "Filter"
      },
      {
        "system": "http://hl7.org/fhir/v3/SpecimenType",
        "version": "1.0.2",
        "code": "FLU",
        "display": "Body fluid, unsp"
      },
      {
        "system": "http://hl7.org/fhir/v3/SpecimenType",
        "version": "1.0.2",
        "code": "FOOD",
        "display": "Food sample"
      },
      {
        "system": "http://hl7.org/fhir/v3/SpecimenType",
        "version": "1.0.2",
        "code": "GAS",
        "display": "Gas"
      },
      {
        "system": "http://hl7.org/fhir/v3/SpecimenType",
        "version": "1.0.2",
        "code": "GAST",
        "display": "Gastric fluid/contents"
      },
      {
        "system": "http://hl7.org/fhir/v3/SpecimenType",
        "version": "1.0.2",
        "code": "GEN",
        "display": "Genital"
      },
      {
        "system": "http://hl7.org/fhir/v3/SpecimenType",
        "version": "1.0.2",
        "code": "GENC",
        "display": "Genital cervix"
      },
      {
        "system": "http://hl7.org/fhir/v3/SpecimenType",
        "version": "1.0.2",
        "code": "GENF",
        "display": "Genital fluid"
      },
      {
        "system": "http://hl7.org/fhir/v3/SpecimenType",
        "version": "1.0.2",
        "code": "GENL",
        "display": "Genital lochia"
      },
      {
        "system": "http://hl7.org/fhir/v3/SpecimenType",
        "version": "1.0.2",
        "code": "GENV",
        "display": "Genital vaginal"
      },
      {
        "system": "http://hl7.org/fhir/v3/SpecimenType",
        "version": "1.0.2",
        "code": "HAR",
        "display": "Hair"
      },
      {
        "system": "http://hl7.org/fhir/v3/SpecimenType",
        "version": "1.0.2",
        "code": "IHG",
        "display": "Inhaled Gas"
      },
      {
        "system": "http://hl7.org/fhir/v3/SpecimenType",
        "version": "1.0.2",
        "code": "ISLT",
        "display": "Isolate"
      },
      {
        "system": "http://hl7.org/fhir/v3/SpecimenType",
        "version": "1.0.2",
        "code": "IT",
        "display": "Intubation tube"
      },
      {
        "system": "http://hl7.org/fhir/v3/SpecimenType",
        "version": "1.0.2",
        "code": "LAM",
        "display": "Lamella"
      },
      {
        "system": "http://hl7.org/fhir/v3/SpecimenType",
        "version": "1.0.2",
        "code": "LIQ",
        "display": "Liquid NOS"
      },
      {
        "system": "http://hl7.org/fhir/v3/SpecimenType",
        "version": "1.0.2",
        "code": "LN",
        "display": "Line"
      },
      {
        "system": "http://hl7.org/fhir/v3/SpecimenType",
        "version": "1.0.2",
        "code": "LNA",
        "display": "Line arterial"
      },
      {
        "system": "http://hl7.org/fhir/v3/SpecimenType",
        "version": "1.0.2",
        "code": "LNV",
        "display": "Line venous"
      },
      {
        "system": "http://hl7.org/fhir/v3/SpecimenType",
        "version": "1.0.2",
        "code": "LYM",
        "display": "Lymphocytes"
      },
      {
        "system": "http://hl7.org/fhir/v3/SpecimenType",
        "version": "1.0.2",
        "code": "MAC",
        "display": "Macrophages"
      },
      {
        "system": "http://hl7.org/fhir/v3/SpecimenType",
        "version": "1.0.2",
        "code": "MAR",
        "display": "Marrow (bone)"
      },
      {
        "system": "http://hl7.org/fhir/v3/SpecimenType",
        "version": "1.0.2",
        "code": "MBLD",
        "display": "Menstrual blood"
      },
      {
        "system": "http://hl7.org/fhir/v3/SpecimenType",
        "version": "1.0.2",
        "code": "MEC",
        "display": "Meconium"
      },
      {
        "system": "http://hl7.org/fhir/v3/SpecimenType",
        "version": "1.0.2",
        "code": "MILK",
        "display": "Breast milk"
      },
      {
        "system": "http://hl7.org/fhir/v3/SpecimenType",
        "version": "1.0.2",
        "code": "MLK",
        "display": "Milk"
      },
      {
        "system": "http://hl7.org/fhir/v3/SpecimenType",
        "version": "1.0.2",
        "code": "NAIL",
        "display": "Nail"
      },
      {
        "system": "http://hl7.org/fhir/v3/SpecimenType",
        "version": "1.0.2",
        "code": "NOS",
        "display": "Nose (nasal passage)"
      },
      {
        "system": "http://hl7.org/fhir/v3/SpecimenType",
        "version": "1.0.2",
        "code": "PAFL",
        "display": "Pancreatic fluid"
      },
      {
        "system": "http://hl7.org/fhir/v3/SpecimenType",
        "version": "1.0.2",
        "code": "PAT",
        "display": "Patient"
      },
      {
        "system": "http://hl7.org/fhir/v3/SpecimenType",
        "version": "1.0.2",
        "code": "PLAS",
        "display": "Plasma"
      },
      {
        "system": "http://hl7.org/fhir/v3/SpecimenType",
        "version": "1.0.2",
        "code": "PLB",
        "display": "Plasma bag"
      },
      {
        "system": "http://hl7.org/fhir/v3/SpecimenType",
        "version": "1.0.2",
        "code": "PLC",
        "display": "Placenta"
      },
      {
        "system": "http://hl7.org/fhir/v3/SpecimenType",
        "version": "1.0.2",
        "code": "PLR",
        "display": "Pleural fluid (thoracentesis fld)"
      },
      {
        "system": "http://hl7.org/fhir/v3/SpecimenType",
        "version": "1.0.2",
        "code": "PMN",
        "display": "Polymorphonuclear neutrophils"
      },
      {
        "system": "http://hl7.org/fhir/v3/SpecimenType",
        "version": "1.0.2",
        "code": "PPP",
        "display": "Platelet poor plasma"
      },
      {
        "system": "http://hl7.org/fhir/v3/SpecimenType",
        "version": "1.0.2",
        "code": "PRP",
        "display": "Platelet rich plasma"
      },
      {
        "system": "http://hl7.org/fhir/v3/SpecimenType",
        "version": "1.0.2",
        "code": "PRT",
        "display": "Peritoneal fluid /ascites"
      },
      {
        "system": "http://hl7.org/fhir/v3/SpecimenType",
        "version": "1.0.2",
        "code": "PUS",
        "display": "Pus"
      },
      {
        "system": "http://hl7.org/fhir/v3/SpecimenType",
        "version": "1.0.2",
        "code": "RBC",
        "display": "Erythrocytes"
      },
      {
        "system": "http://hl7.org/fhir/v3/SpecimenType",
        "version": "1.0.2",
        "code": "SAL",
        "display": "Saliva"
      },
      {
        "system": "http://hl7.org/fhir/v3/SpecimenType",
        "version": "1.0.2",
        "code": "SER",
        "display": "Serum"
      },
      {
        "system": "http://hl7.org/fhir/v3/SpecimenType",
        "version": "1.0.2",
        "code": "SKM",
        "display": "Skeletal muscle"
      },
      {
        "system": "http://hl7.org/fhir/v3/SpecimenType",
        "version": "1.0.2",
        "code": "SKN",
        "display": "Skin"
      },
      {
        "system": "http://hl7.org/fhir/v3/SpecimenType",
        "version": "1.0.2",
        "code": "SMN",
        "display": "Seminal fluid"
      },
      {
        "system": "http://hl7.org/fhir/v3/SpecimenType",
        "version": "1.0.2",
        "code": "SMPLS",
        "display": "Seminal plasma"
      },
      {
        "system": "http://hl7.org/fhir/v3/SpecimenType",
        "version": "1.0.2",
        "code": "SNV",
        "display": "Synovial fluid (Joint fluid)"
      },
      {
        "system": "http://hl7.org/fhir/v3/SpecimenType",
        "version": "1.0.2",
        "code": "SPRM",
        "display": "Spermatozoa"
      },
      {
        "system": "http://hl7.org/fhir/v3/SpecimenType",
        "version": "1.0.2",
        "code": "SPT",
        "display": "Sputum"
      },
      {
        "system": "http://hl7.org/fhir/v3/SpecimenType",
        "version": "1.0.2",
        "code": "SPTC",
        "display": "Sputum - coughed"
      },
      {
        "system": "http://hl7.org/fhir/v3/SpecimenType",
        "version": "1.0.2",
        "code": "SPTT",
        "display": "Sputum - tracheal aspirate"
      },
      {
        "system": "http://hl7.org/fhir/v3/SpecimenType",
        "version": "1.0.2",
        "code": "STL",
        "display": "Stool = Fecal"
      },
      {
        "system": "http://hl7.org/fhir/v3/SpecimenType",
        "version": "1.0.2",
        "code": "SWT",
        "display": "Sweat"
      },
      {
        "system": "http://hl7.org/fhir/v3/SpecimenType",
        "version": "1.0.2",
        "code": "TEAR",
        "display": "Tears"
      },
      {
        "system": "http://hl7.org/fhir/v3/SpecimenType",
        "version": "1.0.2",
        "code": "THRB",
        "display": "Thrombocyte (platelet)"
      },
      {
        "system": "http://hl7.org/fhir/v3/SpecimenType",
        "version": "1.0.2",
        "code": "THRT",
        "display": "Throat"
      },
      {
        "system": "http://hl7.org/fhir/v3/SpecimenType",
        "version": "1.0.2",
        "code": "TISG",
        "display": "Tissue gall bladder"
      },
      {
        "system": "http://hl7.org/fhir/v3/SpecimenType",
        "version": "1.0.2",
        "code": "TISPL",
        "display": "Tissue placenta"
      },
      {
        "system": "http://hl7.org/fhir/v3/SpecimenType",
        "version": "1.0.2",
        "code": "TISS",
        "display": "Tissue, unspecified"
      },
      {
        "system": "http://hl7.org/fhir/v3/SpecimenType",
        "version": "1.0.2",
        "code": "TISU",
        "display": "Tissue ulcer"
      },
      {
        "system": "http://hl7.org/fhir/v3/SpecimenType",
        "version": "1.0.2",
        "code": "TLGI",
        "display": "Tissue large intestine"
      },
      {
        "system": "http://hl7.org/fhir/v3/SpecimenType",
        "version": "1.0.2",
        "code": "TLNG",
        "display": "Tissue lung"
      },
      {
        "system": "http://hl7.org/fhir/v3/SpecimenType",
        "version": "1.0.2",
        "code": "TSMI",
        "display": "Tissue small intestine Tissue ulcer"
      },
      {
        "system": "http://hl7.org/fhir/v3/SpecimenType",
        "version": "1.0.2",
        "code": "TUB",
        "display": "Tube, unspecified"
      },
      {
        "system": "http://hl7.org/fhir/v3/SpecimenType",
        "version": "1.0.2",
        "code": "ULC",
        "display": "Ulcer"
      },
      {
        "system": "http://hl7.org/fhir/v3/SpecimenType",
        "version": "1.0.2",
        "code": "UMB",
        "display": "Umbilical blood"
      },
      {
        "system": "http://hl7.org/fhir/v3/SpecimenType",
        "version": "1.0.2",
        "code": "UMED",
        "display": "Unknown medicine"
      },
      {
        "system": "http://hl7.org/fhir/v3/SpecimenType",
        "version": "1.0.2",
        "code": "UR",
        "display": "Urine"
      },
      {
        "system": "http://hl7.org/fhir/v3/SpecimenType",
        "version": "1.0.2",
        "code": "URC",
        "display": "Urine clean catch"
      },
      {
        "system": "http://hl7.org/fhir/v3/SpecimenType",
        "version": "1.0.2",
        "code": "URNS",
        "display": "Urine sediment"
      },
      {
        "system": "http://hl7.org/fhir/v3/SpecimenType",
        "version": "1.0.2",
        "code": "URT",
        "display": "Urine catheter"
      },
      {
        "system": "http://hl7.org/fhir/v3/SpecimenType",
        "version": "1.0.2",
        "code": "URTH",
        "display": "Urethra"
      },
      {
        "system": "http://hl7.org/fhir/v3/SpecimenType",
        "version": "1.0.2",
        "code": "USUB",
        "display": "Unknown substance"
      },
      {
        "system": "http://hl7.org/fhir/v3/SpecimenType",
        "version": "1.0.2",
        "code": "VOM",
        "display": "Vomitus"
      },
      {
        "system": "http://hl7.org/fhir/v3/SpecimenType",
        "version": "1.0.2",
        "code": "WAT",
        "display": "Water"
      },
      {
        "system": "http://hl7.org/fhir/v3/SpecimenType",
        "version": "1.0.2",
        "code": "WBC",
        "display": "Leukocytes"
      },
      {
        "system": "http://hl7.org/fhir/v3/SpecimenType",
        "version": "1.0.2",
        "code": "WICK",
        "display": "Wick"
      },
      {
        "system": "http://hl7.org/fhir/v3/SpecimenType",
        "version": "1.0.2",
        "code": "WND",
        "display": "Wound"
      },
      {
        "system": "http://hl7.org/fhir/v3/SpecimenType",
        "version": "1.0.2",
        "code": "WNDA",
        "display": "Wound abscess"
      },
      {
        "system": "http://hl7.org/fhir/v3/SpecimenType",
        "version": "1.0.2",
        "code": "WNDD",
        "display": "Wound drainage"
      },
      {
        "system": "http://hl7.org/fhir/v3/SpecimenType",
        "version": "1.0.2",
        "code": "WNDE",
        "display": "Wound exudate"
      }
    ]
  }
}